mypalletizer/__init__.py
mypalletizer/common.py
mypalletizer/generate.py
mypalletizer/log.py
mypalletizer/main.py
mypalletizer/utils.py
mypalletizer-1.0.0b1.dist-info/METADATA
mypalletizer-1.0.0b1.dist-info/WHEEL
mypalletizer-1.0.0b1.dist-info/top_level.txt
mypalletizer-1.0.0b1.dist-info/RECORD
