Metadata-Version: 2.1
Name: mypalletizer
Version: 1.0.0b1
Summary: Python API of serial communication for MyPalletizer series.
Home-page: https://github.com/elephantrobotics/mypalletizer
Author: Zachary zhang
Author-email: lijun.zhang@elephantrobotics.com
License: UNKNOWN
Platform: UNKNOWN
Classifier: Programming Language :: Python :: 2.7
Classifier: Programming Language :: Python :: 3.5
Classifier: Programming Language :: Python :: 3.6
Classifier: Programming Language :: Python :: 3.7
Classifier: Programming Language :: Python :: 3.8
Classifier: Programming Language :: Python :: 3.9
Classifier: License :: OSI Approved :: MIT License
Classifier: Operating System :: OS Independent
Requires-Python: >=2.7, !=3.0.*, !=3.1.*, !=3.2.*, !=3.3.*, != 3.4.*
Requires-Dist: pyserial
